<?xml version="1.0" encoding="utf-8" ?>
<dwsync>
<file name="field_switch.css" server="ftp.govertdev.com//project1/" local="130535463400000000" remote="130567711200000000" Dst="2" />
<file name="field_switch.js" server="ftp.govertdev.com//project1/" local="130535463400000000" remote="130567711200000000" Dst="2" />
<file name="field_switch.less" server="ftp.govertdev.com//project1/" local="130535463400000000" remote="130567711200000000" Dst="2" />
<file name="field_switch.min.js" server="ftp.govertdev.com//project1/" local="130535463400000000" remote="130567711200000000" Dst="2" />
<file name="field_switch.php" server="ftp.govertdev.com//project1/" local="130535463400000000" remote="130567711200000000" Dst="2" />
<file name="field_switch.scss" server="ftp.govertdev.com//project1/" local="130535463400000000" remote="130567711200000000" Dst="2" />
<file name="slider-control.png" server="ftp.govertdev.com//project1/" local="130535463400000000" remote="130567711200000000" Dst="2" />
<file name="switch.gif" server="ftp.govertdev.com//project1/" local="130535463400000000" remote="130567711200000000" Dst="2" />
</dwsync>